setup.py
django_user_metrics.egg-info/PKG-INFO
django_user_metrics.egg-info/SOURCES.txt
django_user_metrics.egg-info/dependency_links.txt
django_user_metrics.egg-info/top_level.txt
user_metrics/__init__.py
user_metrics/admin.py
user_metrics/api.py
user_metrics/models.py
user_metrics/utils.py
user_metrics/management/__init__.py
user_metrics/management/commands/__init__.py
user_metrics/management/commands/metrics_aggregate_by_user.py
user_metrics/migrations/0001_initial.py
user_metrics/migrations/__init__.py