Metadata-Version: 1.0
Name: django-user-metrics
Version: 0.1
Summary: capture metrics for each user
Home-page: https://github.com/rmaceissoft/django-user-metrics
Author: Reiner Marquez
Author-email: rmaceissoft@gmail.com
License: UNKNOWN
Platform: UNKNOWN
Classifier: Development Status :: 4 - Beta
Classifier: Environment :: Console
Classifier: Framework :: Django
Classifier: Intended Audience :: Developers
Classifier: Intended Audience :: Information Technology
Classifier: Operating System :: OS Independent
Classifier: Programming Language :: Python
